easycfg/__init__.py
easycfg/core.py
easycfg-1.0.2.dist-info/LICENSE
easycfg-1.0.2.dist-info/METADATA
easycfg-1.0.2.dist-info/WHEEL
easycfg-1.0.2.dist-info/top_level.txt
easycfg-1.0.2.dist-info/RECORD
