Metadata-Version: 2.1
Name: easycfg
Version: 1.0.2
Summary: A simple package for easy work with cfg files
Home-page: https://github.com/nMagic/easycfg
Author: Dmitriy Glebenkov
Author-email: dvg1995@gmail.com
License: UNKNOWN
Platform: UNKNOWN
Classifier: Programming Language :: Python :: 3
Classifier: License :: OSI Approved :: MIT License
Classifier: Operating System :: OS Independent
Requires-Python: >=3.4
Requires-Dist: PyYAML (==5.1.2)
